LICENSE
MANIFEST.in
README.rst
setup.py
dnsimple/__init__.py
dnsimple/api.py
dnsimple/http.py
dnsimple/utils.py
dnsimple_api.egg-info/PKG-INFO
dnsimple_api.egg-info/SOURCES.txt
dnsimple_api.egg-info/dependency_links.txt
dnsimple_api.egg-info/not-zip-safe
dnsimple_api.egg-info/requires.txt
dnsimple_api.egg-info/top_level.txt