Metadata-Version: 1.1
Name: dnsimple-api
Version: 0.2
Summary: dnsimple.com API wrapper
Home-page: http://github.com/ojii/dnsimple-api
Author: Jonas Obrist
Author-email: jonas.obrist@djee.se
License: BSD
Keywords: dnsimple dns api
Platform: UNKNOWN
Classifier: Development Status :: 4 - Beta
Classifier: Intended Audience :: Developers
Classifier: License :: OSI Approved :: BSD License
Classifier: Topic :: Software Development
Classifier: Programming Language :: Python :: 2
Classifier: Programming Language :: Python :: 2.7
